py_myanmar_numbers_pkg/__init__.py
py_myanmar_numbers_pkg/py_myanmar_numbers/__init__.py
py_myanmar_numbers_pkg/py_myanmar_numbers/converter.py
py_myanmar_numbers_pkg-1.0.1.dist-info/LICENSE
py_myanmar_numbers_pkg-1.0.1.dist-info/METADATA
py_myanmar_numbers_pkg-1.0.1.dist-info/WHEEL
py_myanmar_numbers_pkg-1.0.1.dist-info/top_level.txt
py_myanmar_numbers_pkg-1.0.1.dist-info/RECORD
