Metadata-Version: 2.1
Name: py-myanmar-numbers-pkg
Version: 1.0.1
Summary: Convert Myanmar Numbers to English Numbers
Home-page: https://github.com/ko90thu/py_myanmar_numbers
Author: ko90thu
Author-email: ko90thu@gmail.com
License: UNKNOWN
Platform: UNKNOWN
Classifier: Programming Language :: Python :: 3
Classifier: License :: OSI Approved :: MIT License
Classifier: Operating System :: OS Independent
